[{"id":"IAU-017374","name":"Christian University of Honduras","shortName":"Universidad Cristiana de Honduras (UCRISH)"},{"id":"IAU-027793","name":"Honduras Defense University","shortName":"Universidad de Defensa de Honduras (UDH)"},{"id":"IAU-008981","name":"Honduras National Police University","shortName":"Universidad Nacional de la Policía de Honduras (UNPH)"},{"id":"IAU-017969","name":"Metropolitan University of Honduras","shortName":"Universidad Metropolitana de Honduras (UMH)"},{"id":"IAU-018003","name":"National Autonomous University of Honduras","shortName":"Universidad Nacional Autónoma de Honduras (UNAH)"},{"id":"IAU-017293","name":"Our Lady Queen of Peace Catholic University of Honduras","shortName":"Universidad Católica de Honduras Nuestra Señora Reina de la Paz (UNICAH)"},{"id":"IAU-018218","name":"Polytechnic University of Honduras","shortName":"Universidad Politécnica de Honduras (UPH)"},{"id":"IAU-018391","name":"Technological University of Honduras","shortName":"Universidad Tecnológica de Honduras (UTH)"}]