[{"id":"IAU-000124","name":"Adventist University of the Philippines","shortName":"(AUP)"},{"id":"IAU-000131","name":"Aeronautical Academy of the Philippines","shortName":""},{"id":"IAU-000178","name":"Agro-Industrial Foundation College of the Philippines - Davao","shortName":""},{"id":"IAU-002070","name":"Central Colleges of the Philippines","shortName":""},{"id":"IAU-002087","name":"Central Philippines State University","shortName":""},{"id":"IAU-003568","name":"Data Center College of the Philippines - Baguio City","shortName":""},{"id":"IAU-003569","name":"Data Center College of the Philippines - Bangued, Abra","shortName":""},{"id":"IAU-003570","name":"Data Center College of the Philippines - Laoag City","shortName":""},{"id":"IAU-003571","name":"Data Center College of the Philippines - Vigan City","shortName":""},{"id":"IAU-003695","name":"Development Academy of The Philippines","shortName":"(DAP)"},{"id":"IAU-003781","name":"DMMA College of Southern Philippines","shortName":""},{"id":"IAU-010297","name":"Kester Grant College Philippines","shortName":""},{"id":"IAU-010764","name":"La Consolacion University Philippines","shortName":""},{"id":"IAU-011112","name":"Lyceum of the Philippines University","shortName":""},{"id":"IAU-011112-011109","name":"Lyceum of the Philippines University – Lyceum of the Philippines University  - Batangas","shortName":""},{"id":"IAU-011112-011110","name":"Lyceum of the Philippines University – Lyceum of the Philippines University - Cavite","shortName":""},{"id":"IAU-011112-011108","name":"Lyceum of the Philippines University – Lyceum of the Philippines University - Laguna","shortName":""},{"id":"IAU-011112-011111","name":"Lyceum of the Philippines University – Lyceum of the Philippines University - St. Cabrini College of Allied Medicine","shortName":""},{"id":"IAU-011512","name":"Medical Colleges of Northern Philippines","shortName":""},{"id":"IAU-012833","name":"Northern Philippines College for Maritime Science and Technology","shortName":""},{"id":"IAU-013333","name":"Panpacific University North Philippines","shortName":"(PUNP)"},{"id":"IAU-013497-013496","name":"Philippine Women's University – Philippines Women's College of Davao","shortName":""},{"id":"IAU-013638","name":"Polytechnic University of the Philippines","shortName":"(PUP)"},{"id":"IAU-013852","name":"Quezon Colleges of Southern Philippines","shortName":""},{"id":"IAU-015631","name":"Southern Philippines College of Sciences and Health Education","shortName":""},{"id":"IAU-015632","name":"Southern Philippines College, Cagayan de Oro","shortName":""},{"id":"IAU-015633","name":"Southern Philippines Institute of Science and Technology","shortName":""},{"id":"IAU-015634","name":"Southern Philippines Methodist Colleges","shortName":""},{"id":"IAU-015637","name":"Southern Technological Institute of the Philippines","shortName":""},{"id":"IAU-015670","name":"Southwestern Philippines Foundation College","shortName":""},{"id":"IAU-015750","name":"St. John Technological College of the Philippines","shortName":""},{"id":"IAU-015780-015782","name":"St. Paul University System – St. Paul University Philippines","shortName":"(SPUP)"},{"id":"IAU-015965","name":"Sunrise Christian College Foundation of the Philippines","shortName":""},{"id":"IAU-016260","name":"Technological Institute of the Philippines - Manila","shortName":"(TIP P. Casal)"},{"id":"IAU-016261","name":"Technological University of the Philippines","shortName":"(TUP)"},{"id":"IAU-020149","name":"University of Eastern Philippines","shortName":"(UEP)"},{"id":"IAU-020353","name":"University of Northeastern Philippines","shortName":"(UNEP)"},{"id":"IAU-020357","name":"University of Northern Philippines","shortName":""},{"id":"IAU-020505","name":"University of Southeastern Philippines","shortName":"(USEP)"},{"id":"IAU-020512","name":"University of Southern Philippines Foundation","shortName":""},{"id":"IAU-020568","name":"University of the Philippines System","shortName":""},{"id":"IAU-020568-020564","name":"University of the Philippines System – University of the Philippines - Diliman","shortName":"(U.P. Diliman)"},{"id":"IAU-020568-020570","name":"University of the Philippines System – University of the Philippines - Manila","shortName":""},{"id":"IAU-020568-020566","name":"University of the Philippines System – University of the Philippines Baguio","shortName":"(UPB)"},{"id":"IAU-020568-020567","name":"University of the Philippines System – University of the Philippines Cebu College","shortName":""},{"id":"IAU-020568-020569","name":"University of the Philippines System – University of the Philippines Los Baños","shortName":""},{"id":"IAU-020568-020571","name":"University of the Philippines System – University of the Philippines Mindanao","shortName":"(UPMin)"},{"id":"IAU-020568-020572","name":"University of the Philippines System – University of the Philippines Open University","shortName":"(UPOU)"},{"id":"IAU-020568-020573","name":"University of the Philippines System – University of the Philippines Visayas","shortName":"(UPV)"},{"id":"IAU-020568-020565","name":"University of the Philippines System – University of the Philippines Visayas Tacloban College","shortName":""},{"id":"IAU-021186","name":"Wesleyan University - Philippines","shortName":""},{"id":"IAU-021226","name":"Western Philippines University","shortName":""}]